easier_net/__init__.py
easier_net/easier_net.py
easier_net/execute.py
easier_net/load_uci_classification_data.py
easier_net/load_uci_regression_data.py
easier_net/network.py
easier_net/sier_net.py
EASIER_net-0.0.8.dist-info/LICENSE
EASIER_net-0.0.8.dist-info/METADATA
EASIER_net-0.0.8.dist-info/WHEEL
EASIER_net-0.0.8.dist-info/top_level.txt
EASIER_net-0.0.8.dist-info/RECORD
