Metadata-Version: 2.1
Name: EASIER-net
Version: 0.0.8
Summary: EASIER-net
Home-page: https://github.com/jjfeng/easier_net
Author: Jean Feng
Author-email: jeanfeng@gmail.com
License: UNKNOWN
Platform: UNKNOWN
Classifier: Programming Language :: Python :: 3
Classifier: License :: OSI Approved :: MIT License
Classifier: Operating System :: OS Independent
Requires-Python: >=3.6
License-File: LICENSE
